assignments/5-eng_moahhmed_ALU_VER_SV/COCO_TB/design.sv
module alu (
    input wire clk,
    input wire reset_n,
    input wire [1:0] op_code,
    input wire signed [3:0] A,
    input wire signed [3:0] B,
    output reg signed [3:0] C,
    output reg overflow
);

    // Internal registers to hold the next state of C and overflow
    reg signed [3:0] C_next;
    reg overflow_next;

    // Combinational logic block
    always @(*) begin
        case(op_code)
            2'b00: begin
                C_next = A | B; // Bitwise OR operation
                overflow_next = 1'b0; // No overflow for OR operation
            end
            2'b01: begin
                C_next = A & B; // Bitwise AND operation
                overflow_next = 1'b0; // No overflow for AND operation
            end
            2'b10: begin
                C_next = A + B; // Addition operation
                // Check for overflow in addition
                overflow_next = (A[3] == B[3]) && (A[3] != C_next[3]);
            end
            2'b11: begin
                {overflow_next, C_next} = A - B; // Subtraction operation
                // Check for overflow in subtraction
                overflow_next = (A[3] != B[3]) && (A[3] != C_next[3]);
            end
        endcase
    end

    // Sequential logic block
    always @(posedge clk or negedge reset_n) begin
        if (~reset_n) begin
            overflow <= 1'b0; // Reset overflow flag
            C <= 4'sb0;       // Reset result
        end else begin
            overflow <= overflow_next; // Update overflow flag
            C <= C_next;               // Update result
        end
    end

endmodule

assignments/5-eng_moahhmed_ALU_VER_SV/COCO_TB/top.sv
module top;

    // Declare the clock signal
    reg clk;
    
    // Declare the signals for the ALU
    reg reset_n;
    reg [1:0] op_code;
    reg signed [3:0] A;
    reg signed [3:0] B;
    wire signed [3:0] C;
    wire overflow;

    // Instantiate the ALU module
    alu alu_tb (
        .clk(clk),
        .reset_n(reset_n),
        .op_code(op_code),
        .A(A),
        .B(B),
        .C(C),
        .overflow(overflow)
    );

    // Initial block for simulation
    initial begin
        $dumpfile("file.vcd");
        $dumpvars(0, top);
    end


endmodule

assignments/5-eng_moahhmed_ALU_VER_SV/COCO_TB/file.vcd
$date
    Sep 19, 2024  15:55:55
$end
$version
    TOOL:	xmsim(64)	23.09-s001
$end
$timescale
    1 ps
$end

$scope module top $end
$var reg       1 !    clk $end
$var reg       1 "    reset_n $end
$var reg       2 #    op_code [1:0] $end
$var reg       4 $    A [3:0] $end
$var reg       4 %    B [3:0] $end
$var wire      4 &    C [3:0] $end
$var wire      1 '    overflow  $end

$scope module alu_tb $end
$var wire      1 (    clk  $end
$var wire      1 )    reset_n  $end
$var wire      2 *    op_code [1:0] $end
$var wire      4 +    A [3:0] $end
$var wire      4 ,    B [3:0] $end
$var reg       4 -    C [3:0] $end
$var reg       1 .    overflow $end
$var reg       4 /    C_next [3:0] $end
$var reg       1 0    overflow_next $end
$upscope $end

$upscope $end

$enddefinitions $end
$dumpvars
1!
1"
bx #
bx $
bx %
bx &
x'
1(
1)
bx *
bx +
bx ,
bx -
x.
bx /
x0
$end
#5000
0!
0(
0"
0)
0.
b0 -
b0 &
0'
#10000
1!
1(
#15000
0!
0(
1"
b0 #
b101 $
b11 %
b11 ,
b101 +
b0 *
1)
b111 /
00
#20000
1!
1(
b111 -
b111 &
#25000
0!
0(
b1 #
b1 *
b1 /
#30000
1!
1(
b1 -
b1 &
#35000
0!
0(
b10 #
b1 %
b1 ,
b10 *
b110 /
#40000
1!
1(
b110 -
b110 &
#45000
0!
0(
b11 #
b111 $
b111 +
b11 *
#50000
1!
1(
#55000
0!
0(
b10 #
b111 %
b111 ,
b10 *
b1110 /
10
#60000
1!
1(
1.
b1110 -
b1110 &
1'
#65000
0!
0(
b11 #
b1000 $
b1000 +
b11 *
b1 /
#70000
1!
1(
b1 -
b1 &
#75000
0!
0(
#80000
1!
1(
#85000
0!
0(
#90000
1!
1(
#95000
0!
0(
#100000
1!
1(
#105000
0!
0(
#110000
1!
1(
#115000
0!
0(
#120000
1!
1(
#125000
0!
0(
b100 $
b1000 %
b1000 ,
b100 +
b1100 /
00
10
#130000
1!
1(
b1100 -
b1100 &
#135000
0!
0(
b1001 $
b1 %
b1 ,
b1001 +
b1000 /
00
#140000
1!
1(
0.
b1000 -
b1000 &
0'
#145000
0!
0(
b0 #
b1011 $
b1110 %
b1110 ,
b1011 +
b0 *
b1111 /
#150000
1!
1(
b1111 -
b1111 &
#155000
0!
0(
b11 #
b11 $
b1100 %
b1100 ,
b11 +
b11 *
b111 /
#160000
1!
1(
b111 -
b111 &
#165000
0!
0(
b10 #
b111 $
b1011 %
b1011 ,
b111 +
b10 *
b10 /
#170000
1!
1(
b10 -
b10 &
#175000
0!
0(
b1 #
b1001 $
b1101 %
b1101 ,
b1001 +
b1 *
b1001 /
#180000
1!
1(
b1001 -
b1001 &
#185000
0!
0(
b11 #
b1010 $
b0 %
b0 ,
b1010 +
b11 *
b1010 /
10
00
#190000
1!
1(
b1010 -
b1010 &
#195000
0!
0(
b0 #
b1011 $
b1011 +
b0 *
b1011 /
#200000
1!
1(
b1011 -
b1011 &
#205000
0!
0(
b10 #
b1101 %
b1101 ,
b10 *
b1000 /
#210000
1!
1(
b1000 -
b1000 &
#215000
0!
0(
b1100 %
b1100 ,
b111 /
10
#220000
1!
1(
1.
b111 -
b111 &
1'
#225000
0!
0(
b11 $
b0 %
b0 ,
b11 +
b11 /
00
#230000
1!
1(
0.
b11 -
b11 &
0'
#235000
0!
0(
b0 #
b1111 $
b1010 %
b1010 ,
b1111 +
b0 *
b1111 /
#240000
1!
1(
b1111 -
b1111 &
#245000
0!
0(
b1011 $
b110 %
b110 ,
b1011 +
#250000
1!
1(
#255000
0!
0(
b1 #
b1110 $
b1001 %
b1001 ,
b1110 +
b1 *
b1000 /
#260000
1!
1(
b1000 -
b1000 &
#265000
0!
0(
b10 #
b10 $
b11 %
b11 ,
b10 +
b10 *
b101 /
#270000
1!
1(
b101 -
b101 &
#275000
0!
0(
b1000 $
b1100 %
b1100 ,
b1000 +
b100 /
10
#280000
1!
1(
1.
b100 -
b100 &
1'
#285000
0!
0(
b0 #
b11 $
b111 %
b111 ,
b11 +
b0 *
b111 /
00
#290000
1!
1(
0.
b111 -
b111 &
0'
#295000
0!
0(
b1 $
b11 %
b11 ,
b1 +
b11 /
#300000
1!
1(
b11 -
b11 &
#305000
0!
0(
b10 #
b1111 $
b1011 %
b1011 ,
b1111 +
b10 *
b1010 /
#310000
1!
1(
b1010 -
b1010 &
#315000
0!
0(
b11 #
b100 $
b111 %
b111 ,
b100 +
b11 *
b1101 /
10
00
#320000
1!
1(
b1101 -
b1101 &
#325000
0!
0(
b1100 $
b1111 %
b1111 ,
b1100 +
10
00
#330000
1!
1(
#335000
0!
0(
b10 #
b10 $
b100 %
b100 ,
b10 +
b10 *
b110 /
#340000
1!
1(
b110 -
b110 &
#345000
0!
0(
b110 $
b0 %
b0 ,
b110 +
#350000
1!
1(
#355000
0!
0(
b1011 %
b1011 ,
b1 /
#360000
1!
1(
b1 -
b1 &
#365000
0!
0(
b0 #
b0 $
b100 %
b100 ,
b0 +
b0 *
b100 /
#370000
1!
1(
b100 -
b100 &
#375000
0!
0(
b10 #
b101 $
b111 %
b111 ,
b101 +
b10 *
b1100 /
10
#380000
1!
1(
1.
b1100 -
b1100 &
1'
#385000
0!
0(
b11 #
b1011 $
b1101 %
b1101 ,
b1011 +
b11 *
b1110 /
00
#390000
1!
1(
0.
b1110 -
b1110 &
0'
#395000
0!
0(
b0 #
b100 $
b100 %
b100 ,
b100 +
b0 *
b100 /
#400000
1!
1(
b100 -
b100 &
#405000
0!
0(
b11 #
b1010 $
b0 %
b0 ,
b1010 +
b11 *
b1010 /
10
00
#410000
1!
1(
b1010 -
b1010 &
#415000
0!
0(
b10 #
b1110 $
b100 %
b100 ,
b1110 +
b10 *
b10 /
#420000
1!
1(
b10 -
b10 &
#425000
0!
0(
b0 #
b1 $
b110 %
b110 ,
b1 +
b0 *
b111 /
#430000
1!
1(
b111 -
b111 &
#435000
0!
0(
b1111 $
b1100 %
b1100 ,
b1111 +
b1111 /
#440000
1!
1(
b1111 -
b1111 &
#445000
0!
0(
b10 #
b1100 $
b1101 %
b1101 ,
b1100 +
b10 *
b1001 /
#450000
1!
1(
b1001 -
b1001 &
#455000
0!
0(
b0 #
b101 $
b100 %
b100 ,
b101 +
b0 *
b101 /
#460000
1!
1(
b101 -
b101 &
#465000
0!
0(
b1 #
b1100 $
b1 %
b1 ,
b1100 +
b1 *
b0 /
#470000
1!
1(
b0 -
b0 &
#475000
0!
0(
b10 #
b1011 $
b1101 %
b1101 ,
b1011 +
b10 *
b1000 /
#480000
1!
1(
b1000 -
b1000 &
#485000
0!
0(
b11 #
b0 $
b100 %
b100 ,
b0 +
b11 *
b1100 /
10
00
#490000
1!
1(
b1100 -
b1100 &
#495000
0!
0(
b10 %
b10 ,
b1110 /
10
00
#500000
1!
1(
b1110 -
b1110 &
#505000
0!
0(
b1 #
b1000 $
b1111 %
b1111 ,
b1000 +
b1 *
b1000 /
#510000
1!
1(
b1000 -
b1000 &
#515000
0!
0(
b0 #
b101 $
b110 %
b110 ,
b101 +
b0 *
b111 /
#520000
1!
1(
b111 -
b111 &
#525000
0!
0(
b1101 $
b1110 %
b1110 ,
b1101 +
b1111 /
#530000
1!
1(
b1111 -
b1111 &
#535000
0!
0(
b1 #
b1100 $
b10 %
b10 ,
b1100 +
b1 *
b0 /
#540000
1!
1(
b0 -
b0 &
#545000
0!
0(
b0 #
b1000 $
b1011 %
b1011 ,
b1000 +
b0 *
b1011 /
#550000
1!
1(
b1011 -
b1011 &
#555000
0!
0(
b10 #
b1110 %
b1110 ,
b10 *
b110 /
10
#560000
1!
1(
1.
b110 -
b110 &
1'
#565000
0!
0(
b1001 $
b1001 %
b1001 ,
b1001 +
b10 /
#570000
1!
1(
b10 -
b10 &
#575000
0!
0(
b11 #
b1011 $
b11 %
b11 ,
b1011 +
b11 *
b1000 /
00
#580000
1!
1(
0.
b1000 -
b1000 &
0'
#585000
0!
0(
b1 #
b100 $
b100 %
b100 ,
b100 +
b1 *
b100 /
#590000
1!
1(
b100 -
b100 &
#595000
0!
0(
b0 #
b0 $
b1111 %
b1111 ,
b0 +
b0 *
b1111 /
#600000
1!
1(
b1111 -
b1111 &
#605000
0!
0(
b10 #
b10 $
b1001 %
b1001 ,
b10 +
b10 *
b1011 /
#610000
1!
1(
b1011 -
b1011 &
#615000
0!
0(
b11 #
b100 $
b1110 %
b1110 ,
b100 +
b11 *
b110 /
#620000
1!
1(
b110 -
b110 &
#625000
0!
0(
b0 #
b1001 $
b110 %
b110 ,
b1001 +
b0 *
b1111 /
#630000
1!
1(
b1111 -
b1111 &
#635000
0!
0(
b1 #
b1010 $
b1100 %
b1100 ,
b1010 +
b1 *
b1000 /
#640000
1!
1(
b1000 -
b1000 &
#645000
0!
0(
b0 #
b10 $
b0 %
b0 ,
b10 +
b0 *
b10 /
#650000
1!
1(
b10 -
b10 &
#655000
0!
0(
b1 #
b1101 $
b1001 %
b1001 ,
b1101 +
b1 *
b1001 /
#660000
1!
1(
b1001 -
b1001 &
#665000
0!
0(
b111 $
b1010 %
b1010 ,
b111 +
b10 /
#670000
1!
1(
b10 -
b10 &
#675000
0!
0(
b10 #
b1001 $
b1001 %
b1001 ,
b1001 +
b10 *
10
#680000
1!
1(
1.
1'
#685000
0!
0(
b1 #
b0 $
b100 %
b100 ,
b0 +
b1 *
b0 /
00
#690000
1!
1(
0.
b0 -
b0 &
0'
#695000
0!
0(
b10 #
b1100 %
b1100 ,
b10 *
b1100 /
#700000
1!
1(
b1100 -
b1100 &
#705000
0!
0(
b0 #
b111 $
b111 +
b0 *
b1111 /
#710000
1!
1(
b1111 -
b1111 &
#715000
0!
0(
b10 #
b1 $
b1000 %
b1000 ,
b1 +
b10 *
b1001 /
#720000
1!
1(
b1001 -
b1001 &
#725000
0!
0(
b0 #
b11 $
b0 %
b0 ,
b11 +
b0 *
b11 /
#730000
1!
1(
b11 -
b11 &
#735000
0!
0(
b1 #
b1101 $
b111 %
b111 ,
b1101 +
b1 *
b101 /
#740000
1!
1(
b101 -
b101 &
#745000
0!
0(
b100 $
b1 %
b1 ,
b100 +
b0 /
#750000
1!
1(
b0 -
b0 &
#755000
0!
0(
b0 #
b0 $
b1010 %
b1010 ,
b0 +
b0 *
b1010 /
#760000
1!
1(
b1010 -
b1010 &
#765000
0!
0(
b1 #
b101 $
b10 %
b10 ,
b101 +
b1 *
b0 /
#770000
1!
1(
b0 -
b0 &
#775000
0!
0(
b11 #
b1 $
b11 %
b11 ,
b1 +
b11 *
b1110 /
10
00
#780000
1!
1(
b1110 -
b1110 &
#785000
0!
0(
b10 #
b1110 $
b111 %
b111 ,
b1110 +
b10 *
b101 /
#790000
1!
1(
b101 -
b101 &
#795000
0!
0(
b0 #
b100 $
b1011 %
b1011 ,
b100 +
b0 *
b1111 /
#800000
1!
1(
b1111 -
b1111 &
#805000
0!
0(
b1011 $
b111 %
b111 ,
b1011 +
#810000
1!
1(
#815000
0!
0(
b10 #
b1110 $
b1110 %
b1110 ,
b1110 +
b10 *
b1100 /
#820000
1!
1(
b1100 -
b1100 &
#825000
0!
0(
b0 #
b110 $
b1010 %
b1010 ,
b110 +
b0 *
b1110 /
#830000
1!
1(
b1110 -
b1110 &
#835000
0!
0(
b1 #
b11 $
b101 %
b101 ,
b11 +
b1 *
b1 /
#840000
1!
1(
b1 -
b1 &
#845000
0!
0(
b1111 $
b10 %
b10 ,
b1111 +
b10 /
#850000
1!
1(
b10 -
b10 &
#855000
0!
0(
b10 #
b110 $
b110 %
b110 ,
b110 +
b10 *
b1100 /
10
#860000
1!
1(
1.
b1100 -
b1100 &
1'
#865000
0!
0(
b0 #
b1 $
b1000 %
b1000 ,
b1 +
b0 *
b1001 /
00
#870000
1!
1(
0.
b1001 -
b1001 &
0'
#875000
0!
0(
b1010 $
b1101 %
b1101 ,
b1010 +
b1111 /
#880000
1!
1(
b1111 -
b1111 &
#885000
0!
0(
b1 #
b0 $
b0 +
b1 *
b0 /
#890000
1!
1(
b0 -
b0 &
#895000
0!
0(
b10 #
b110 $
b1 %
b1 ,
b110 +
b10 *
b111 /
#900000
1!
1(
b111 -
b111 &
#905000
0!
0(
b1 #
b10 $
b1110 %
b1110 ,
b10 +
b1 *
b10 /
#910000
1!
1(
b10 -
b10 &
#915000
0!
0(
b0 #
b1100 $
b0 %
b0 ,
b1100 +
b0 *
b1100 /
#920000
1!
1(
b1100 -
b1100 &
#925000
0!
0(
b11 #
b1101 $
b100 %
b100 ,
b1101 +
b11 *
b1001 /
10
00
#930000
1!
1(
b1001 -
b1001 &
#935000
0!
0(
b0 #
b11 $
b1000 %
b1000 ,
b11 +
b0 *
b1011 /
#940000
1!
1(
b1011 -
b1011 &
#945000
0!
0(
b1 #
b1011 $
b11 %
b11 ,
b1011 +
b1 *
b11 /
#950000
1!
1(
b11 -
b11 &
#955000
0!
0(
b1 $
b1 %
b1 ,
b1 +
b1 /
#960000
1!
1(
b1 -
b1 &
#965000
0!
0(
b10 #
b10 $
b1100 %
b1100 ,
b10 +
b10 *
b1110 /
#970000
1!
1(
b1110 -
b1110 &
#975000
0!
0(
b1 #
b1110 $
b1110 %
b1110 ,
b1110 +
b1 *
#980000
1!
1(
#985000
0!
0(
b10 #
b100 $
b111 %
b111 ,
b100 +
b10 *
b1011 /
10
#990000
1!
1(
1.
b1011 -
b1011 &
1'
#995000
0!
0(
b0 $
b0 +
b111 /
00
#1000000
1!
1(
0.
b111 -
b111 &
0'
#1005000
0!
0(
b1 $
b1101 %
b1101 ,
b1 +
b1110 /
#1010000
1!
1(
b1110 -
b1110 &
#1015000
0!
0(
b11 #
b1110 $
b1 %
b1 ,
b1110 +
b11 *
b1101 /
10
00
#1020000
1!
1(
b1101 -
b1101 &
#1025000
0!
0(
b0 #
b10 $
b1010 %
b1010 ,
b10 +
b0 *
b1010 /
#1030000
1!
1(
b1010 -
b1010 &
#1035000
0!
0(
b110 $
b101 %
b101 ,
b110 +
b111 /
#1040000
1!
1(
b111 -
b111 &
#1045000
0!
0(
b10 #
b10 $
b1 %
b1 ,
b10 +
b10 *
b11 /
#1050000
1!
1(
b11 -
b11 &
#1055000
0!
0(
b11 #
b1111 $
b1111 +
b11 *
b1110 /
10
00
#1060000
1!
1(
b1110 -
b1110 &
#1065000
0!
0(
b10 #
b1001 $
b1111 %
b1111 ,
b1001 +
b10 *
b1000 /
#1070000
1!
1(
b1000 -
b1000 &
#1075000
0!
0(
b11 $
b111 %
b111 ,
b11 +
b1010 /
10
#1080000
1!
1(
1.
b1010 -
b1010 &
1'
#1085000
0!
0(
b11 #
b1101 $
b1010 %
b1010 ,
b1101 +
b11 *
b11 /
00
#1090000
1!
1(
0.
b11 -
b11 &
0'
#1095000
0!
0(
b0 #
b1001 $
b11 %
b11 ,
b1001 +
b0 *
b1011 /
#1100000
1!
1(
b1011 -
b1011 &
#1105000
0!
0(
b101 $
b1101 %
b1101 ,
b101 +
b1101 /
#1110000
1!
1(
b1101 -
b1101 &
#1115000
0!
0(
b1 #
b111 $
b1111 %
b1111 ,
b111 +
b1 *
b111 /
#1120000
1!
1(
b111 -
b111 &
#1125000
0!
0(
b10 #
b101 $
b1101 %
b1101 ,
b101 +
b10 *
b10 /
#1130000
1!
1(
b10 -
b10 &
#1135000
0!
0(
b11 #
b10 $
b1 %
b1 ,
b10 +
b11 *
b1 /
#1140000
1!
1(
b1 -
b1 &
#1145000
0!
0(
b0 #
b1011 $
b1101 %
b1101 ,
b1011 +
b0 *
b1111 /
#1150000
1!
1(
b1111 -
b1111 &
#1155000
0!
0(
b11 #
b111 $
b101 %
b101 ,
b111 +
b11 *
b10 /
#1160000
1!
1(
b10 -
b10 &
#1165000
0!
0(
b0 #
b101 $
b1001 %
b1001 ,
b101 +
b0 *
b1101 /
#1170000
1!
1(
b1101 -
b1101 &
#1175000
0!
0(
b11 #
b10 $
b100 %
b100 ,
b10 +
b11 *
b1110 /
10
00
#1180000
1!
1(
b1110 -
b1110 &
#1185000
0!
0(
b10 #
b1111 $
b1111 %
b1111 ,
b1111 +
b10 *
#1190000
1!
1(
#1195000
0!
0(
b1 #
b10 $
b1001 %
b1001 ,
b10 +
b1 *
b0 /
#1200000
1!
1(
b0 -
b0 &
#1205000
0!
0(
b10 #
b1011 $
b11 %
b11 ,
b1011 +
b10 *
b1110 /
#1210000
1!
1(
b1110 -
b1110 &
#1215000
0!
0(
b101 $
b10 %
b10 ,
b101 +
b111 /
#1220000
1!
1(
b111 -
b111 &
#1225000
0!
0(
b1 #
b1000 $
b1100 %
b1100 ,
b1000 +
b1 *
b1000 /
#1230000
1!
1(
b1000 -
b1000 &
#1235000
0!
0(
b11 $
b1111 %
b1111 ,
b11 +
b11 /
#1240000
1!
1(
b11 -
b11 &
#1245000
0!
0(
b0 #
b1100 $
b1101 %
b1101 ,
b1100 +
b0 *
b1101 /
#1250000
1!
1(
b1101 -
b1101 &
#1255000
0!
0(
b11 #
b1 $
b110 %
b110 ,
b1 +
b11 *
b1011 /
10
00
#1260000
1!
1(
b1011 -
b1011 &
#1265000
0!
0(
b110 $
b100 %
b100 ,
b110 +
b10 /
#1270000
1!
1(
b10 -
b10 &
#1275000
0!
0(
b10 #
b1100 $
b1110 %
b1110 ,
b1100 +
b10 *
b1010 /
#1280000
1!
1(
b1010 -
b1010 &
#1285000
0!
0(
b1000 $
b1001 %
b1001 ,
b1000 +
b1 /
10
#1290000
1!
1(
1.
b1 -
b1 &
1'
#1295000
0!
0(
b1 #
b1010 $
b101 %
b101 ,
b1010 +
b1 *
b0 /
00
#1300000
1!
1(
0.
b0 -
b0 &
0'
#1305000
0!
0(
b1111 $
b1 %
b1 ,
b1111 +
b1 /
#1310000
1!
1(
b1 -
b1 &
#1315000
0!
0(
b11 #
b1001 $
b111 %
b111 ,
b1001 +
b11 *
b10 /
10
#1320000
1!
1(
1.
b10 -
b10 &
1'
#1325000
0!
0(
b111 $
b1001 %
b1001 ,
b111 +
b1110 /
00
10
#1330000
1!
1(
b1110 -
b1110 &
#1335000
0!
0(
b0 $
b1100 %
b1100 ,
b0 +
b100 /
00
#1340000
1!
1(
0.
b100 -
b100 &
0'
#1345000
0!
0(
b0 #
b101 $
b100 %
b100 ,
b101 +
b0 *
b101 /
#1350000
1!
1(
b101 -
b101 &
#1355000
0!
0(
b1 #
b11 $
b1 %
b1 ,
b11 +
b1 *
b1 /
#1360000
1!
1(
b1 -
b1 &
#1365000
0!
0(
b100 $
b110 %
b110 ,
b100 +
b100 /
#1370000
1!
1(
b100 -
b100 &
#1375000
0!
0(
b110 $
b1000 %
b1000 ,
b110 +
b0 /
#1380000
1!
1(
b0 -
b0 &
#1385000
0!
0(
b0 #
b1010 $
b100 %
b100 ,
b1010 +
b0 *
b1110 /
#1390000
1!
1(
b1110 -
b1110 &
#1395000
0!
0(
b1110 %
b1110 ,
#1400000
1!
1(
#1405000
0!
0(
b11 #
b1011 $
b111 %
b111 ,
b1011 +
b11 *
b100 /
10
#1410000
1!
1(
1.
b100 -
b100 &
1'
#1415000
0!
0(
b1010 $
b1100 %
b1100 ,
b1010 +
b1110 /
00
#1420000
1!
1(
0.
b1110 -
b1110 &
0'
#1425000
0!
0(
b10 #
b1000 $
b111 %
b111 ,
b1000 +
b10 *
b1111 /
#1430000
1!
1(
b1111 -
b1111 &
#1435000
0!
0(
b11 #
b1011 $
b1 %
b1 ,
b1011 +
b11 *
b1010 /
10
00
#1440000
1!
1(
b1010 -
b1010 &
#1445000
0!
0(
b0 $
b1010 %
b1010 ,
b0 +
b110 /
#1450000
1!
1(
b110 -
b110 &
#1455000
0!
0(
b10 #
b1101 $
b1011 %
b1011 ,
b1101 +
b10 *
b1000 /
#1460000
1!
1(
b1000 -
b1000 &
#1465000
0!
0(
b0 #
b1001 $
b1111 %
b1111 ,
b1001 +
b0 *
b1111 /
#1470000
1!
1(
b1111 -
b1111 &
#1475000
0!
0(
b1110 $
b111 %
b111 ,
b1110 +
#1480000
1!
1(
#1485000
0!
0(
b11 #
b1111 $
b1111 +
b11 *
b1000 /
10
00
#1490000
1!
1(
b1000 -
b1000 &
#1495000
0!
0(
b10 #
b1011 $
b110 %
b110 ,
b1011 +
b10 *
b1 /
#1500000
1!
1(
b1 -
b1 &
#1505000
0!
0(
b110 $
b0 %
b0 ,
b110 +
b110 /
#1510000
1!
1(
b110 -
b110 &
#1515000
0!
0(
b11 #
b1 $
b100 %
b100 ,
b1 +
b11 *
b1101 /
10
00
#1520000
1!
1(
b1101 -
b1101 &
#1525000
0!
0(
b11 %
b11 ,
b1110 /
10
00
#1530000
1!
1(
b1110 -
b1110 &
#1535000
0!
0(
b10 $
b100 %
b100 ,
b10 +
10
00
#1540000
1!
1(
#1545000
0!
0(
b1001 $
b1110 %
b1110 ,
b1001 +
b1011 /
10
00
#1550000
1!
1(
b1011 -
b1011 &
#1555000
0!
0(
b1101 %
b1101 ,
b1100 /
10
00
#1560000
1!
1(
b1100 -
b1100 &
#1565000
0!
0(
b0 #
b11 $
b1100 %
b1100 ,
b11 +
b0 *
b1111 /
#1570000
1!
1(
b1111 -
b1111 &
#1575000
0!
0(
b1 #
b1 $
b1 %
b1 ,
b1 +
b1 *
b1 /
#1580000
1!
1(
b1 -
b1 &
#1585000
0!
0(
b11 $
b110 %
b110 ,
b11 +
b10 /
#1590000
1!
1(
b10 -
b10 &
#1595000
0!
0(
b0 #
b1110 $
b11 %
b11 ,
b1110 +
b0 *
b1111 /
#1600000
1!
1(
b1111 -
b1111 &
#1605000
0!
0(
b10 #
b1001 $
b110 %
b110 ,
b1001 +
b10 *
#1610000
1!
1(
#1615000
0!
0(
b1 #
b1000 $
b1110 %
b1110 ,
b1000 +
b1 *
b1000 /
#1620000
1!
1(
b1000 -
b1000 &
#1625000
0!
0(
b0 #
b0 $
b1011 %
b1011 ,
b0 +
b0 *
b1011 /
#1630000
1!
1(
b1011 -
b1011 &
#1635000
0!
0(
b11 #
b101 $
b101 +
b11 *
b1010 /
10
#1640000
1!
1(
1.
b1010 -
b1010 &
1'
#1645000
0!
0(
b10 #
b1010 $
b100 %
b100 ,
b1010 +
b10 *
b1110 /
00
#1650000
1!
1(
0.
b1110 -
b1110 &
0'
#1655000
0!
0(
b1 #
b1001 %
b1001 ,
b1 *
b1000 /
#1660000
1!
1(
b1000 -
b1000 &
#1665000
0!
0(
b10 #
b1101 $
b1000 %
b1000 ,
b1101 +
b10 *
b101 /
10
#1670000
1!
1(
1.
b101 -
b101 &
1'
#1675000
0!
0(
b0 #
b100 $
b101 %
b101 ,
b100 +
b0 *
00
#1680000
1!
1(
0.
0'
#1685000
0!
0(
b11 #
b11 $
b111 %
b111 ,
b11 +
b11 *
b1100 /
10
00
#1690000
1!
1(
b1100 -
b1100 &
#1695000
0!
0(
b100 %
b100 ,
b1111 /
10
00
#1700000
1!
1(
b1111 -
b1111 &
#1705000
0!
0(
b0 #
b110 $
b1100 %
b1100 ,
b110 +
b0 *
b1110 /
#1710000
1!
1(
b1110 -
b1110 &
#1715000
0!
0(
b10 #
b1111 $
b100 %
b100 ,
b1111 +
b10 *
b11 /
#1720000
1!
1(
b11 -
b11 &
#1725000
0!
0(
b11 #
b110 $
b10 %
b10 ,
b110 +
b11 *
b100 /
#1730000
1!
1(
b100 -
b100 &
#1735000
0!
0(
b10 #
b100 $
b111 %
b111 ,
b100 +
b10 *
b1011 /
10
#1740000
1!
1(
1.
b1011 -
b1011 &
1'
#1745000
0!
0(
b0 #
b110 $
b10 %
b10 ,
b110 +
b0 *
b110 /
00
#1750000
1!
1(
0.
b110 -
b110 &
0'
#1755000
0!
0(
b10 #
b1011 $
b1011 %
b1011 ,
b1011 +
b10 *
10
#1760000
1!
1(
1.
1'
#1765000
0!
0(
b11 #
b101 $
b1101 %
b1101 ,
b101 +
b11 *
b1000 /
00
10
#1770000
1!
1(
b1000 -
b1000 &
#1775000
0!
0(
b0 #
b0 *
b1101 /
00
#1780000
1!
1(
0.
b1101 -
b1101 &
0'
#1785000
0!
0(
b1001 %
b1001 ,
#1790000
1!
1(
#1795000
0!
0(
b1010 $
b1011 %
b1011 ,
b1010 +
b1011 /
#1800000
1!
1(
b1011 -
b1011 &
#1805000
0!
0(
b10 #
b1000 $
b101 %
b101 ,
b1000 +
b10 *
b1101 /
#1810000
1!
1(
b1101 -
b1101 &
#1815000
0!
0(
b1111 $
b1000 %
b1000 ,
b1111 +
b111 /
10
#1820000
1!
1(
1.
b111 -
b111 &
1'
#1825000
0!
0(
b1 #
b101 $
b1001 %
b1001 ,
b101 +
b1 *
b1 /
00
#1830000
1!
1(
0.
b1 -
b1 &
0'
#1835000
0!
0(
b10 #
b1001 $
b1001 +
b10 *
b10 /
10
#1840000
1!
1(
1.
b10 -
b10 &
1'
#1845000
0!
0(
b1 #
b11 $
b1110 %
b1110 ,
b11 +
b1 *
00
#1850000
1!
1(
0.
0'
#1855000
0!
0(
b11 #
b1100 $
b1011 %
b1011 ,
b1100 +
b11 *
b1 /
#1860000
1!
1(
b1 -
b1 &
#1865000
0!
0(
b1101 %
b1101 ,
b1111 /
10
00
#1870000
1!
1(
b1111 -
b1111 &
#1875000
0!
0(
b10 #
b100 $
b111 %
b111 ,
b100 +
b10 *
b1011 /
10
#1880000
1!
1(
1.
b1011 -
b1011 &
1'
#1885000
0!
0(
b11 #
b1101 $
b1011 %
b1011 ,
b1101 +
b11 *
b10 /
00
#1890000
1!
1(
0.
b10 -
b10 &
0'
#1895000
0!
0(
b1 #
b11 $
b101 %
b101 ,
b11 +
b1 *
b1 /
#1900000
1!
1(
b1 -
b1 &
#1905000
0!
0(
b11 #
b10 $
b10 %
b10 ,
b10 +
b11 *
b0 /
#1910000
1!
1(
b0 -
b0 &
#1915000
0!
0(
b101 $
b1001 %
b1001 ,
b101 +
b1100 /
10
#1920000
1!
1(
1.
b1100 -
b1100 &
1'
#1925000
0!
0(
b10 #
b10 $
b1101 %
b1101 ,
b10 +
b10 *
b1111 /
00
#1930000
1!
1(
0.
b1111 -
b1111 &
0'
#1935000
0!
0(
b0 #
b110 $
b1010 %
b1010 ,
b110 +
b0 *
b1110 /
#1940000
1!
1(
b1110 -
b1110 &
#1945000
0!
0(
b10 #
b1110 $
b100 %
b100 ,
b1110 +
b10 *
b10 /
#1950000
1!
1(
b10 -
b10 &
#1955000
0!
0(
b11 #
b1001 $
b1010 %
b1010 ,
b1001 +
b11 *
b1111 /
10
00
#1960000
1!
1(
b1111 -
b1111 &
#1965000
0!
0(
b10 #
b1100 $
b1101 %
b1101 ,
b1100 +
b10 *
b1001 /
#1970000
1!
1(
b1001 -
b1001 &
#1975000
0!
0(
b11 #
b1010 $
b1010 +
b11 *
b1101 /
10
00
#1980000
1!
1(
b1101 -
b1101 &
#1985000
0!
0(
b1 #
b1100 $
b1011 %
b1011 ,
b1100 +
b1 *
b1000 /
#1990000
1!
1(
b1000 -
b1000 &
#1995000
0!
0(
b10 #
b110 $
b1010 %
b1010 ,
b110 +
b10 *
b0 /
#2000000
1!
1(
b0 -
b0 &
#2005000
0!
0(
b0 #
b1 $
b111 %
b111 ,
b1 +
b0 *
b111 /
#2010000
1!
1(
b111 -
b111 &
#2015000
0!
0(
b1 #
b1000 $
b11 %
b11 ,
b1000 +
b1 *
b0 /
#2020000
1!
1(
b0 -
b0 &
#2025000
0!
0(
b10 #
b1011 $
b110 %
b110 ,
b1011 +
b10 *
b1 /
#2030000
1!
1(
b1 -
b1 &
#2035000
0!
0(
b0 #
b110 $
b1000 %
b1000 ,
b110 +
b0 *
b1110 /
#2040000
1!
1(
b1110 -
b1110 &
#2045000
0!
0(
b10 #
b1001 $
b1111 %
b1111 ,
b1001 +
b10 *
b1000 /
#2050000
1!
1(
b1000 -
b1000 &
#2055000
0!
0(
b1010 $
b101 %
b101 ,
b1010 +
b1111 /
#2060000
1!
1(
b1111 -
b1111 &
